latex2mathml/__init__.py
latex2mathml/commands.py
latex2mathml/converter.py
latex2mathml/exceptions.py
latex2mathml/symbols_parser.py
latex2mathml/tokenizer.py
latex2mathml/unimathsymbols.txt
latex2mathml/walker.py
latex2mathml-3.75.5.dist-info/LICENSE
latex2mathml-3.75.5.dist-info/METADATA
latex2mathml-3.75.5.dist-info/WHEEL
latex2mathml-3.75.5.dist-info/entry_points.txt
latex2mathml-3.75.5.dist-info/RECORD
